LICENSE
MANIFEST.in
README.md
setup.py
project_tehnocat/__init__.py
project_tehnocat/assistant_bot_main.py
project_tehnocat/birthdays.py
project_tehnocat/command.py
project_tehnocat/command_parser.py
project_tehnocat/consol.py
project_tehnocat/contact_record.py
project_tehnocat/phone_book.py
project_tehnocat.egg-info/PKG-INFO
project_tehnocat.egg-info/SOURCES.txt
project_tehnocat.egg-info/dependency_links.txt
project_tehnocat.egg-info/entry_points.txt
project_tehnocat.egg-info/requires.txt
project_tehnocat.egg-info/top_level.txt
project_tehnocat/utils/__init__.py
project_tehnocat/utils/cli_parse_decorator.py
project_tehnocat/utils/console_history.py
project_tehnocat/utils/demo_data.py
project_tehnocat/utils/dump_decorator.py
project_tehnocat/utils/validator.py
project_tehnocat/utils/vim.py
tests/test_main.py