Metadata-Version: 2.1
Name: project_tehnocat
Version: 1.0.8
Summary: Personal assistant CLI tool. Manage your contacts and notes.
Home-page: https://github.com/st3n/project-TehnoCat
Author: TehnoCat Team
Author-email: tehnocat@example.com
License: MIT
License-File: LICENSE
Requires-Dist: prompt_toolkit
Requires-Dist: jaro-winkler
Requires-Dist: rich
Requires-Dist: faker
Requires-Dist: gnureadline
